[
  {
    "name": "AsuraComic",
    "pkg": "eu.kanade.tachiyomi.extension.en.asuracomic",
    "apk": "https://github.com/Asmith007/tachiyomi-asuracomic/releases/download/v1.0/asuracomic-v1.0.apk",
    "lang": "en",
    "code": 1,
    "version": "1.0",
    "nsfw": 0,
    "hasReadme": 1,
    "hasChangelog": 1,
    "sources": [
      {
        "name": "AsuraComic",
        "lang": "en",
        "id": "1000000001",
        "baseUrl": "https://asuracomic.net",
        "versionId": 1,
        "hasCloudflare": 0
      }
    ]
  }
]
